{
  "slug": "background-beams-with-collision",
  "name": "Background Beams With Collision",
  "category": [
    "backgrounds",
    "layout"
  ],
  "tags": [
    "animated",
    "atmospheric",
    "background",
    "beams",
    "collision",
    "decorative",
    "with"
  ],
  "summary": "An advanced background effect featuring animated light beams that dynamically collide and interact, creating an engaging visual spectacle perfect for modern, tech-focused designs.",
  "detailedDescription": "Background Beams With Collision takes the classic light beam effect and adds sophisticated physics-based interactions where beams dynamically collide, bounce, and intersect in real-time. This creates a living, breathing background that feels algorithmically generated rather than pre-animated. Each beam behaves as an independent entity with its own trajectory, speed, and visual properties, and when beams meet, they create interaction effects including color blending, brightness changes, or particle bursts. The component uses canvas-based rendering for optimal performance with multiple simultaneous beams, ensuring smooth animation even with complex collision scenarios. Visual customization includes beam count, speed, color palettes, collision behavior, glow intensity, and trail effects. The result is a dynamic, ever-changing background that maintains visual interest over extended viewing periods without becoming repetitive. Perfect for tech product launches, SaaS landing pages, gaming interfaces, or any context where conveying innovation and technical sophistication is important. The effect works particularly well in dark mode contexts where the luminous beams create dramatic contrast. Despite its visual complexity, the component is optimized to run at 60fps on modern devices through efficient collision detection and GPU-accelerated rendering.",
  "purpose": [
    "Create dynamic, algorithmically-generated backgrounds that feel alive and unique",
    "Convey technical sophistication and innovation through physics-based visuals",
    "Provide engaging visual interest that maintains appeal over extended viewing",
    "Support tech-focused brand identities with futuristic, cutting-edge aesthetics",
    "Differentiate interfaces through distinctive, memorable visual effects"
  ],
  "behavior": [
    "Generates multiple light beams with independent trajectories and properties",
    "Detects and responds to beam collisions with realistic interaction effects",
    "Applies physics-based motion including velocity, direction changes, and bouncing",
    "Creates visual interaction effects at collision points (blending, bursts, etc.)",
    "Continuously generates new beams while removing old ones for sustained effect",
    "Maintains smooth 60fps canvas rendering with optimized collision detection",
    "Responds to configuration for beam count, speed, colors, and behavior"
  ],
  "visualCharacteristics": [
    "Dynamic, ever-changing visual patterns from real-time beam interactions",
    "Luminous light beams with glowing edges and soft gradients",
    "Visible collision effects creating moments of visual interest",
    "Futuristic, tech-forward aesthetic suitable for innovation-focused brands",
    "Deep, rich colors particularly effective against dark backgrounds",
    "Complex, algorithmic appearance that feels computationally generated"
  ],
  "difficulty": "beginner",
  "designTone": [
    "modern",
    "premium"
  ],
  "layoutRole": "decorative",
  "recommendations": [
    "Best for premium landing page sections and hero compositions.",
    "Use as a supporting atmospheric layer rather than the primary layout structure."
  ],
  "dependencies": [
    "clsx",
    "motion",
    "tailwind-merge"
  ],
  "installCommand": "npx shadcn@latest add @aceternity/background-beams-with-collision",
  "registryUrl": "https://ui.aceternity.com/registry/background-beams-with-collision.json",
  "docsUrl": "https://ui.aceternity.com/components/background-beams-with-collision",
  "previewAvailable": true,
  "examples": [
    "https://ui.aceternity.com/components/background-beams-with-collision"
  ],
  "compatibility": {
    "react": true,
    "nextjs": true,
    "tailwind": true,
    "framerMotion": true,
    "shadcn": true
  },
  "scores": {
    "visualIntensity": 7,
    "animationIntensity": 6,
    "layoutImportance": 3,
    "customizationEase": 7,
    "landingPageFit": 8,
    "dashboardFit": 3,
    "performanceImpact": 6
  }
}
